MANIFEST.in
README.md
easytime.py
setup.py
easytime.egg-info/PKG-INFO
easytime.egg-info/SOURCES.txt
easytime.egg-info/dependency_links.txt
easytime.egg-info/not-zip-safe
easytime.egg-info/requires.txt
easytime.egg-info/top_level.txt