Metadata-Version: 1.0
Name: easytime
Version: 0.1.2
Summary: The simplest python time library ever written.
Home-page: https://github.com/rdegges/easytime
Author: Randall Degges
Author-email: rdegges@gmail.com
License: UNLICENSE
Keywords: python time simple easy timezone
Platform: UNKNOWN
